{
    "lab1_A": [
        [-22, -2, -6, 6],
        [3, -17, -3, 7],
        [2, 6, -17, 5],
        [-1, -8, 8, 23]
    ],
    "lab1_b": [
        96,
        -26,
        35,
        -234
    ],
    "lab2_A": [
        [-1, -1, 0, 0, 0],
        [7, -17, -8, 0, 0],
        [0, -9, 19, 8, 0],
        [0, 0, 7, -20, 4],
        [0, 0, 0, -4, 12]
    ],
    "lab2_b": [
        -4,
        132,
        -59,
        -193,
        -40
    ],
    "lab3_A": [
        [-22, -2, -6, 6],
        [3, -17, -3, 7],
        [2, 6, -17, 5],
        [-1, -8, 8, 23]
    ],
    "lab3_b": [
        96,
        -26,
        35,
        -234
    ],
    "lab4_A": [
        [-7, -5, -9],
        [-5, 5, 2],
        [-9, 2, 9]
    ],
    "lab4_b": [],
    "lab5_A": [
        [2, -4, 5],
        [-5, -2, -3],
        [1, -8, -3]
    ],
    "lab5_b": []
}
